swarmauri_certs_x509/X509CertService.py
swarmauri_certs_x509/__init__.py
swarmauri_certs_x509-0.2.0.dev4.dist-info/METADATA
swarmauri_certs_x509-0.2.0.dev4.dist-info/WHEEL
swarmauri_certs_x509-0.2.0.dev4.dist-info/entry_points.txt
swarmauri_certs_x509-0.2.0.dev4.dist-info/RECORD
